{
  "usuarios": [],
  "lojas": [
    {
      "id": 1,
      "nome": "Pizzaria Oliveira",
      "categoria": "Pizzas",
      "imagem": "Pizza",
      "status": "Ativa"
    },
    {
      "id": 2,
      "nome": "Burger da Mari",
      "categoria": "Lanches",
      "imagem": "UtensilsCrossed",
      "status": "Ativa"
    },
    {
      "id": 3,
      "nome": "Doçuras da Ana",
      "categoria": "Doceria",
      "imagem": "CakeSlice",
      "status": "Ativa"
    },
    {
      "id": 4,
      "nome": "Tanaka Sushi",
      "categoria": "Japonesa",
      "imagem": "Fish",
      "status": "Ativa"
    }
  ],
  "produtos": []
}